xpe/__init__.py
xpe-1.0.8.data/scripts/xpe
xpe-1.0.8.dist-info/LICENSE.txt
xpe-1.0.8.dist-info/METADATA
xpe-1.0.8.dist-info/WHEEL
xpe-1.0.8.dist-info/top_level.txt
xpe-1.0.8.dist-info/RECORD
