Metadata-Version: 2.1
Name: xpe
Version: 1.0.8
Summary: A versatile commandline xpath parser
Home-page: https://github.com/charmparticle/xpe
Author: github.com/charmparticle
License: BSD 3-Clause License
Platform: UNKNOWN
Classifier: Programming Language :: Python :: 3
Classifier: Operating System :: OS Independent
License-File: LICENSE.txt
Requires-Dist: chardet
Requires-Dist: lxml
